MANIFEST.in
README.txt
setup.py
yampy/__init__.py
yampy/authenticator.py
yampy/client.py
yampy/constants.py
yampy/errors.py
yampy/models.py
yampy/yammer.py
yampy.egg-info/PKG-INFO
yampy.egg-info/SOURCES.txt
yampy.egg-info/dependency_links.txt
yampy.egg-info/requires.txt
yampy.egg-info/top_level.txt
yampy/apis/__init__.py
yampy/apis/messages.py
yampy/apis/users.py
yampy/apis/utils.py