Metadata-Version: 1.0
Name: yampy
Version: 1.0
Summary: The official Python client for Yammer's API
Home-page: http://github.com/yammer/yam-python
Author: Yammer
Author-email: blyttle@yammer-inc.com
License: Apache
Platform: UNKNOWN
Classifier: Development Status :: 3 - Alpha
Classifier: License :: OSI Approved :: Apache Software License
